ggshield-1.46.0.dist-info/METADATA
ggshield-1.46.0.dist-info/WHEEL
ggshield-1.46.0.dist-info/entry_points.txt
ggshield-1.46.0.dist-info/licenses/LICENSE
ggshield/__init__.py
ggshield/__main__.py
ggshield/cmd/__init__.py
ggshield/cmd/auth/__init__.py
ggshield/cmd/auth/login.py
ggshield/cmd/auth/logout.py
ggshield/cmd/config/__init__.py
ggshield/cmd/config/config_get.py
ggshield/cmd/config/config_list.py
ggshield/cmd/config/config_migrate.py
ggshield/cmd/config/config_set.py
ggshield/cmd/config/config_unset.py
ggshield/cmd/config/constants.py
ggshield/cmd/hmsl/__init__.py
ggshield/cmd/hmsl/api_status.py
ggshield/cmd/hmsl/check.py
ggshield/cmd/hmsl/check_secret_manager/__init__.py
ggshield/cmd/hmsl/check_secret_manager/hashicorp_vault.py
ggshield/cmd/hmsl/decrypt.py
ggshield/cmd/hmsl/fingerprint.py
ggshield/cmd/hmsl/hmsl_common_options.py
ggshield/cmd/hmsl/hmsl_utils.py
ggshield/cmd/hmsl/query.py
ggshield/cmd/hmsl/quota.py
ggshield/cmd/honeytoken/__init__.py
ggshield/cmd/honeytoken/create.py
ggshield/cmd/honeytoken/create_with_context.py
ggshield/cmd/honeytoken/utils.py
ggshield/cmd/install.py
ggshield/cmd/quota.py
ggshield/cmd/secret/__init__.py
ggshield/cmd/secret/ignore.py
ggshield/cmd/secret/scan/__init__.py
ggshield/cmd/secret/scan/archive.py
ggshield/cmd/secret/scan/changes.py
ggshield/cmd/secret/scan/ci.py
ggshield/cmd/secret/scan/docker.py
ggshield/cmd/secret/scan/dockerarchive.py
ggshield/cmd/secret/scan/docset.py
ggshield/cmd/secret/scan/path.py
ggshield/cmd/secret/scan/precommit.py
ggshield/cmd/secret/scan/prepush.py
ggshield/cmd/secret/scan/prereceive.py
ggshield/cmd/secret/scan/pypi.py
ggshield/cmd/secret/scan/range.py
ggshield/cmd/secret/scan/repo.py
ggshield/cmd/secret/scan/secret_scan_common_options.py
ggshield/cmd/secret/scan/ui_utils.py
ggshield/cmd/status.py
ggshield/cmd/utils/__init__.py
ggshield/cmd/utils/common_decorators.py
ggshield/cmd/utils/common_options.py
ggshield/cmd/utils/context_obj.py
ggshield/cmd/utils/debug.py
ggshield/cmd/utils/files.py
ggshield/cmd/utils/hooks.py
ggshield/cmd/utils/output_format.py
ggshield/cmd/utils/quota.py
ggshield/core/__init__.py
ggshield/core/cache.py
ggshield-1.46.0.dist-info/RECORD
