Metadata-Version: 2.1
Name: ggshield
Version: 1.46.0
Summary: Detect secrets from all sources using GitGuardian's brains
Keywords: cli,devsecops,secrets-detection,security-tools,gitguardian
Author-Email: GitGuardian <support@gitguardian.com>
Maintainer-Email: GitGuardian <support@gitguardian.com>
License: MIT
Classifier: Development Status :: 5 - Production/Stable
Classifier: Intended Audience :: Developers
Classifier: Intended Audience :: End Users/Desktop
Classifier: Natural Language :: English
Classifier: License :: OSI Approved :: MIT License
Classifier: Environment :: Console
Classifier: Programming Language :: Python
Classifier: Programming Language :: Python :: 3
Classifier: Programming Language :: Python :: 3.10
Classifier: Programming Language :: Python :: 3.11
Classifier: Programming Language :: Python :: 3.12
Classifier: Programming Language :: Python :: 3.9
Classifier: Operating System :: OS Independent
Classifier: Topic :: Security
Project-URL: Homepage, https://github.com/GitGuardian/ggshield
Requires-Python: >=3.9
Requires-Dist: platformdirs~=3.0.0
Requires-Dist: charset-normalizer~=3.1.0
Requires-Dist: click~=8.1.0
Requires-Dist: cryptography~=43.0.1
Requires-Dist: marshmallow~=3.18.0
Requires-Dist: marshmallow-dataclass~=8.5.8
Requires-Dist: oauthlib~=3.2.1
Requires-Dist: pygitguardian~=1.28.0
Requires-Dist: pyjwt~=2.6.0
Requires-Dist: python-dotenv~=0.21.0
Requires-Dist: pyyaml~=6.0.1
Requires-Dist: requests~=2.32.0
Requires-Dist: rich~=12.5.1
Requires-Dist: typing-extensions~=4.12.2
Requires-Dist: urllib3~=2.2.2
Requires-Dist: truststore>=0.10.1; python_version >= "3.10"
